scikit_robot-0.2.43.dist-info/licenses/LICENSE
skrobot/__init__.py
skrobot/_lazy_imports.py
skrobot/interpolator.py
skrobot/optimizer.py
skrobot/pycompat.py
skrobot/apps/__init__.py
skrobot/apps/change_urdf_root.py
skrobot/apps/cli.py
skrobot/apps/convert_urdf_mesh.py
skrobot/apps/convert_urdf_to_primitives.py
skrobot/apps/convert_wheel_collision.py
skrobot/apps/extract_sub_urdf.py
skrobot/apps/generate_robot_class.py
skrobot/apps/modularize_urdf.py
skrobot/apps/scale_urdf.py
skrobot/apps/transform_urdf.py
skrobot/apps/urdf_hash.py
skrobot/apps/visualize_mesh.py
skrobot/apps/visualize_urdf.py
skrobot/backend/__init__.py
skrobot/backend/jax_backend.py
skrobot/backend/numpy_backend.py
skrobot/backend/registry.py
skrobot/collision/__init__.py
skrobot/collision/distance.py
skrobot/collision/geometry.py
skrobot/collision/robot_collision.py
skrobot/coordinates/__init__.py
skrobot/coordinates/base.py
skrobot/coordinates/dual_quaternion.py
skrobot/coordinates/geo.py
skrobot/coordinates/math.py
skrobot/coordinates/quaternion.py
skrobot/data/__init__.py
skrobot/data/kuka_description/kuka.urdf
skrobot/data/kuka_description/meshes/finger_base_left.stl
skrobot/data/kuka_description/meshes/finger_base_right.stl
skrobot/data/kuka_description/meshes/finger_tip_left.stl
skrobot/data/kuka_description/meshes/finger_tip_right.stl
skrobot/data/kuka_description/meshes/link_0.mtl
skrobot/data/kuka_description/meshes/link_0.obj
skrobot/data/kuka_description/meshes/link_0.stl
skrobot/data/kuka_description/meshes/link_1.mtl
skrobot/data/kuka_description/meshes/link_1.obj
skrobot/data/kuka_description/meshes/link_1.stl
skrobot/data/kuka_description/meshes/link_2.mtl
skrobot/data/kuka_description/meshes/link_2.obj
skrobot/data/kuka_description/meshes/link_2.stl
skrobot/data/kuka_description/meshes/link_3.mtl
skrobot/data/kuka_description/meshes/link_3.obj
skrobot/data/kuka_description/meshes/link_3.stl
skrobot/data/kuka_description/meshes/link_4.mtl
skrobot/data/kuka_description/meshes/link_4.obj
scikit_robot-0.2.43.dist-info/METADATA
scikit_robot-0.2.43.dist-info/WHEEL
scikit_robot-0.2.43.dist-info/entry_points.txt
scikit_robot-0.2.43.dist-info/top_level.txt
scikit_robot-0.2.43.dist-info/RECORD
