Metadata-Version: 2.4
Name: scikit-robot
Version: 0.2.43
Summary: A Flexible Framework for Robot Control in Python
Home-page: https://github.com/iory/scikit-robot
Author: iory
Author-email: ab.ioryz@gmail.com
License: MIT
Classifier: Development Status :: 5 - Production/Stable
Classifier: Intended Audience :: Developers
Classifier: Natural Language :: English
Classifier: License :: OSI Approved :: MIT License
Classifier: Programming Language :: Python
Classifier: Programming Language :: Python :: 3.8
Classifier: Programming Language :: Python :: 3.9
Classifier: Programming Language :: Python :: 3.10
Classifier: Programming Language :: Python :: 3.11
Classifier: Programming Language :: Python :: 3.12
Classifier: Programming Language :: Python :: 3.13
Classifier: Programming Language :: Python :: Implementation :: CPython
License-File: LICENSE
Requires-Dist: cached-property; python_version >= "3.0"
Requires-Dist: cached-property<=1.5.2; python_version < "3.0"
Requires-Dist: filelock
Requires-Dist: future
Requires-Dist: gdown
Requires-Dist: lxml
Requires-Dist: networkx>=2.2.0; python_version < "3.8"
Requires-Dist: networkx>=2.5; python_version >= "3.8"
Requires-Dist: numpy>=1.16.0; python_version < "3.8"
Requires-Dist: numpy>=1.21.0; python_version >= "3.8"
Requires-Dist: ordered_set
Requires-Dist: packaging
Requires-Dist: pillow
Requires-Dist: pycollada<0.9; python_version < "3.2"
Requires-Dist: pycollada<=0.9,>=0.8; python_version >= "3.2" and python_version < "3.9"
Requires-Dist: pycollada>=0.8; python_version >= "3.9"
Requires-Dist: pyglet<2.0
Requires-Dist: pysdfgen>=0.2.0
Requires-Dist: repoze.lru; python_version < "3.2"
Requires-Dist: rtree
Requires-Dist: scikit-learn; python_version < "3.8"
Requires-Dist: scikit-learn>=0.24.0; python_version >= "3.8"
Requires-Dist: scikit-robot-pyrender>=0.1.47
Requires-Dist: scipy; python_version >= "3.0" and python_version < "3.8"
Requires-Dist: scipy<=1.2.3; python_version < "3.0"
Requires-Dist: scipy>=1.6.3; python_version >= "3.8"
Requires-Dist: six
Requires-Dist: trimesh!=3.23.0,>=3.9.0
Requires-Dist: viser
Provides-Extra: opt
Requires-Dist: cvxopt; extra == "opt"
Requires-Dist: quadprog; extra == "opt"
Provides-Extra: docs
Requires-Dist: sphinx>=1.8.2; extra == "docs"
Requires-Dist: sphinx_rtd_theme; extra == "docs"
Provides-Extra: all
Requires-Dist: pybullet>=2.1.9; extra == "all"
Requires-Dist: fast-simplification; extra == "all"
Requires-Dist: jax; extra == "all"
Requires-Dist: jaxlib; extra == "all"
Requires-Dist: sphinx>=1.8.2; extra == "all"
Requires-Dist: sphinx_rtd_theme; extra == "all"
Requires-Dist: cvxopt; extra == "all"
Requires-Dist: quadprog; extra == "all"
Dynamic: author
Dynamic: author-email
Dynamic: classifier
Dynamic: description
Dynamic: description-content-type
Dynamic: home-page
Dynamic: license
Dynamic: license-file
Dynamic: provides-extra
Dynamic: requires-dist
Dynamic: summary
